[
    {
        "quote": "What does freedom really mean, when demanded of you by a god",
        "author": ""
    },
    {
        "quote": "Cling no longer to past grievances but hold tight to memory this act of benevolence",
        "author": ""
    },
    {
        "quote": "Your time is limited, don't waste it living someone else's life.",
        "author": "Steve Jobs"
    },
    {
        "quote": "Life is what happens when you're busy making other plans.",
        "author": "John Lennon"
    },
    {
        "quote": "The best way to predict the future is to create it.",
        "author": "Peter Drucker"
    },
    {
        "quote": "Success is not final, failure is not fatal: It is the courage to continue that counts.",
        "author": "Winston Churchill"
    }
]
